{"cameraMode":{"drawMode":0,"name":"Shaded","section":"Shading Mode"},"sceneLighting":false,"audioPlay":false,"sceneViewState":{"m_AlwaysRefresh":false,"showFog":true,"showSkybox":false,"showFlares":true,"showImageEffects":true,"showParticleSystems":true,"showVisualEffectGraphs":true,"m_FxEnabled":true},"in2DMode":false,"pivot":{"x":-2.2194290161132814,"y":6.433253288269043,"z":3.450763702392578},"rotation":{"x":0.3720778226852417,"y":-0.3091217279434204,"z":0.13295811414718629,"w":0.8650585412979126},"size":0.15399408340454102,"orthographic":false}